pystow/.DS_Store
pystow/__init__.py
pystow/__main__.py
pystow/api.py
pystow/cache.py
pystow/cli.py
pystow/config_api.py
pystow/constants.py
pystow/git.py
pystow/github.py
pystow/graph.py
pystow/impl.py
pystow/py.typed
pystow/utils.py
pystow/version.py
pystow-0.7.19.dist-info/licenses/LICENSE
pystow-0.7.19.dist-info/WHEEL
pystow-0.7.19.dist-info/entry_points.txt
pystow-0.7.19.dist-info/METADATA
pystow-0.7.19.dist-info/RECORD
