Metadata-Version: 2.4
Name: pystow
Version: 0.7.19
Summary: Easily pick a place to store data for your Python code
Keywords: snekpack,cookiecutter,caching,file management
Author: Charles Tapley Hoyt
Author-email: Charles Tapley Hoyt <cthoyt@gmail.com>
License-File: LICENSE
Classifier: Development Status :: 5 - Production/Stable
Classifier: Environment :: Console
Classifier: Intended Audience :: Developers
Classifier: License :: OSI Approved :: MIT License
Classifier: Operating System :: OS Independent
Classifier: Framework :: Pytest
Classifier: Framework :: tox
Classifier: Framework :: Sphinx
Classifier: Natural Language :: English
Classifier: Programming Language :: Python
Classifier: Programming Language :: Python :: 3.10
Classifier: Programming Language :: Python :: 3.11
Classifier: Programming Language :: Python :: 3.12
Classifier: Programming Language :: Python :: 3.13
Classifier: Programming Language :: Python :: 3.14
Classifier: Programming Language :: Python :: 3 :: Only
Classifier: Typing :: Typed
Requires-Dist: click
Requires-Dist: requests
Requires-Dist: tqdm
Requires-Dist: typing-extensions
Requires-Dist: boto3 ; extra == 'aws'
Requires-Dist: bs4 ; extra == 'bs4'
Requires-Dist: sphinx>=8 ; extra == 'docs'
Requires-Dist: sphinx-rtd-theme>=3.0 ; extra == 'docs'
Requires-Dist: sphinx-click ; extra == 'docs'
Requires-Dist: sphinx-automodapi ; extra == 'docs'
Requires-Dist: pandas ; extra == 'pandas'
Requires-Dist: pydantic ; extra == 'pydantic'
Requires-Dist: ratelimit ; extra == 'ratelimit'
Requires-Dist: rdflib ; extra == 'rdf'
Requires-Dist: pytest ; extra == 'tests'
Requires-Dist: coverage[toml] ; extra == 'tests'
Requires-Dist: requests-file ; extra == 'tests'
Requires-Dist: lxml ; extra == 'xml'
Requires-Dist: pyyaml ; extra == 'yaml'
Maintainer: Charles Tapley Hoyt
Maintainer-email: Charles Tapley Hoyt <cthoyt@gmail.com>
Requires-Python: >=3.10
Project-URL: Bug Tracker, https://github.com/cthoyt/pystow/issues
Project-URL: Homepage, https://github.com/cthoyt/pystow
Project-URL: Repository, https://github.com/cthoyt/pystow.git
Project-URL: Documentation, https://pystow.readthedocs.io
Project-URL: Funding, https://github.com/sponsors/cthoyt
Provides-Extra: aws
Provides-Extra: bs4
Provides-Extra: docs
Provides-Extra: pandas
Provides-Extra: pydantic
Provides-Extra: ratelimit
Provides-Extra: rdf
Provides-Extra: tests
Provides-Extra: xml
Provides-Extra: yaml
